shark/__init__.py
shark/api_urls.py
shark/dashboard.py
shark/models.py
shark/settings_base.py
shark/tests.py
shark/urls.py
shark/wsgi.py
shark/accounting/__init__.py
shark/accounting/models.py
shark/accounting/urls.py
shark/accounting/views.py
shark/banking/__init__.py
shark/banking/admin.py
shark/banking/models.py
shark/banking/migrations/0001_initial.py
shark/banking/migrations/0002_add_currency.py
shark/banking/migrations/__init__.py
shark/base/__init__.py
shark/base/formats/__init__.py
shark/base/formats/de/__init__.py
shark/base/formats/de/formats.py
shark/base/formats/en/__init__.py
shark/base/formats/en/formats.py
shark/billing/__init__.py
shark/billing/admin.py
shark/billing/admin_forms.py
shark/billing/admin_urls.py
shark/billing/admin_views.py
shark/billing/api_serializers.py
shark/billing/api_urls.py
shark/billing/api_views.py
shark/billing/dashboard.py
shark/billing/models.py
shark/billing/tests.py
shark/billing/migrations/0001_initial.py
shark/billing/migrations/0002_add_item_type_and_payment_type.py
shark/billing/migrations/0003_meta_changes.py
shark/billing/migrations/0004_new_address_fields.py
shark/billing/migrations/0005_convert_address.py
shark/billing/migrations/__init__.py
shark/customer/__init__.py
shark/customer/admin.py
shark/customer/api_serializers.py
shark/customer/autocomplete_light_registry.py
shark/customer/models.py
shark/customer/tests.py
shark/customer/migrations/0001_initial.py
shark/customer/migrations/0002_add_hourly_rate.py
shark/customer/migrations/0003_extra_fields_and_customer_address.py
shark/customer/migrations/0004_add_various_fields.py
shark/customer/migrations/0005_customercontact_customer.py
shark/customer/migrations/0006_add_address_addition_2.py
shark/customer/migrations/0007_add_state.py
shark/customer/migrations/0008_convert_address.py
shark/customer/migrations/__init__.py
shark/documents/__init__.py
shark/documents/admin.py
shark/documents/models.py
shark/documents/migrations/0001_initial.py
shark-0.0.1.dist-info/LICENSE
shark-0.0.1.dist-info/METADATA
shark-0.0.1.dist-info/WHEEL
shark-0.0.1.dist-info/top_level.txt
shark-0.0.1.dist-info/RECORD
